wellen/inputs/icarus/wellen-issue-137-icarus_dumpall_tb.v
// Testbench that makes Icarus Verilog emit mid-file $dumpall checkpoints.
//
// Build & run:
//   iverilog -o tb.vvp tb.v
//   vvp tb.vvp
// Produces icarus_dumpall.vcd
`timescale 1ns/1ns
module tb;
  reg clk = 0;
  reg [7:0] cnt = 0;

  always #5 clk = ~clk;            // posedges at 5, 15, 25, 35, ...

  always @(posedge clk) begin
    cnt <= cnt + 8'd1;             // NBA: lands after the checkpoint below
    if (cnt == 8'd3)               // old value read => fires at t=35
      $dumpall;                    // mid-timestep checkpoint
  end

  initial begin
    $dumpfile("icarus_dumpall.vcd");
    $dumpvars(0, tb);
    #52 $dumpall;                  // second checkpoint at a quiet time
    #28 $finish;                   // stop at t=80
  end
endmodule

wellen/inputs/icarus/wellen-issue-137-icarus_dumpall.vcd
$date
	Mon Jul 20 09:48:33 2026
$end
$version
	Icarus Verilog
$end
$timescale
	1ns
$end
$scope module tb $end
$var reg 1 ! clk $end
$var reg 8 " cnt [7:0] $end
$upscope $end
$enddefinitions $end
$comment Show the parameter values. $end
$dumpall
$end
#0
$dumpvars
b0 "
0!
$end
#5
b1 "
1!
#10
0!
#15
b10 "
1!
#20
0!
#25
b11 "
1!
#30
0!
#35
$dumpall
b11 "
1!
$end
b100 "
1!
#40
0!
#45
b101 "
1!
#50
0!
#52
$dumpall
b101 "
0!
$end
#55
b110 "
1!
#60
0!
#65
b111 "
1!
#70
0!
#75
b1000 "
1!
